{
  "_id": "page.start",
  "_type": "page.start",
  "body": "Use this form to request personal information about you held by Her Majesty's Prison and Probation Service.\r\n\r\nSubmitting a request should take around 5 minutes.\r\n\r\nSo we can give you the best service, you should be as clear as you can about the information you need.",
  "components": [
    {
      "$component": true,
      "$content": true,
      "$definition": true,
      "_id": "page.start--inset",
      "_type": "inset",
      "html": "We aim to respond to all requests within a month."
    },
    {
      "_id": "page.start--content",
      "_type": "content",
      "html": "### Before you start \r\n\r\nYou will need to provide some personal details to help us find your information  faster: \r\n\r\n* your name\r\n* prison number\r\n* date of birth.\r\n\r\nThe more information you can provide, the quicker we will be able to respond to your request.\r\n\r\nWe may charge you a fee to process your request if it is excessive. We will contact you to discuss before proceeding with the request.\r\n\r\nThis request will be submitted under Rule 39 which means only you will have access to any information we send you. \r\n\r\nWe will only send information once so you may wish to consider sharing it with your solicitor.\r\n\r\n**We can only send your information to you. If you want your information to be sent to someone else, such as your solicitor or a relative, they will need to submit a request on your behalf.**"
    }
  ],
  "extraComponents": [
    {
      "_id": "page.start--content--2",
      "_type": "content",
      "html": "You can also request via letter.\r\n\r\nThe online service is also available in Welsh (Cymraeg)."
    }
  ],
  "heading": "Request your personal information",
  "steps": [
    "page.where-would-you-like-information-from",
    "page._exit",
    "page._application-about-court-case",
    "page.application-your-name",
    "page.application-your-date-of-birth",
    "page._application-nomis-number",
    "page._application-which-prison",
    "page.what-prisons-information-would-you-like",
    "page.prison-date-range",
    "page._prisons-cctv",
    "page.prison-telephone-recordings",
    "page.probation-name-of-probation-officer--2",
    "page.probation-information-requested",
    "page.probation-period",
    "page.probation-cctv-details",
    "page.courts-what-information",
    "page._opg-what-info",
    "page._laa-what-info",
    "page._other-what-info",
    "page.check-your-answers",
    "page.confirmation"
  ],
  "url": "/"
}